notch/__init__.py
notch-2026.0.dist-info/WHEEL
notch-2026.0.dist-info/METADATA
notch-2026.0.dist-info/RECORD
