Metadata-Version: 2.4
Name: notch
Version: 2026.0
Summary: The Python logging micropackage
Author: William Jackson
Author-email: William Jackson <william@subtlecoolness.com>
License-Expression: MIT
Classifier: Development Status :: 5 - Production/Stable
Classifier: Intended Audience :: Developers
Classifier: Operating System :: OS Independent
Classifier: Programming Language :: Python :: 3
Classifier: Topic :: Software Development
Classifier: Topic :: System :: Logging
Requires-Python: >=3.10
Project-URL: Changes, https://github.com/williamjacksn/notch/releases
Project-URL: Homepage, https://github.com/williamjacksn/notch
Project-URL: Issues, https://github.com/williamjacksn/notch/issues
